meator/__init__.py
meator/_constants.py
meator/_utils/__init__.py
meator/_utils/sentinel_default.py
meator/dispatchers/__init__.py
meator/dispatchers/base.py
meator/dispatchers/command.py
meator/dispatchers/errors.py
meator/dispatchers/query.py
meator/entities/__init__.py
meator/entities/command.py
meator/entities/event.py
meator/entities/query.py
meator/entities/request.py
meator/errors.py
meator/interfaces/__init__.py
meator/interfaces/dispatcher/__init__.py
meator/interfaces/dispatcher/command.py
meator/interfaces/dispatcher/interface.py
meator/interfaces/dispatcher/query.py
meator/interfaces/handlers/__init__.py
meator/interfaces/handlers/command.py
meator/interfaces/handlers/event.py
meator/interfaces/handlers/query.py
meator/interfaces/handlers/request.py
meator/interfaces/middleware.py
meator/interfaces/observer/__init__.py
meator/interfaces/observer/event.py
meator/interfaces/observer/interface.py
meator/interfaces/types.py
meator/middlewares/__init__.py
meator/middlewares/wrap_handler.py
meator/observers/__init__.py
meator/observers/base.py
meator/observers/event.py
meator/py.typed
meator-2.0.1.dist-info/LICENSE
meator-2.0.1.dist-info/METADATA
meator-2.0.1.dist-info/WHEEL
meator-2.0.1.dist-info/RECORD
