Metadata-Version: 2.1
Name: meator
Version: 2.0.1
Summary: Mediator pattern impl
Home-page: https://pypi.org/project/meator/
License: MIT
Keywords: dispatcher,command,event,query,mediator,cqrs
Author: likeinlife
Author-email: likeinlife@outlook.com
Requires-Python: >=3.11,<4.0
Classifier: Intended Audience :: Developers
Classifier: License :: OSI Approved :: MIT License
Classifier: Operating System :: OS Independent
Classifier: Programming Language :: Python
Classifier: Programming Language :: Python :: 3
Classifier: Programming Language :: Python :: 3.11
Classifier: Programming Language :: Python :: 3.12
Classifier: Programming Language :: Python :: 3 :: Only
Classifier: Programming Language :: Python :: 3.13
Classifier: Topic :: Software Development :: Libraries :: Python Modules
Project-URL: Documentation, https://github.com/likeinlife/cqrs_mediator/wiki
Project-URL: Repository, https://github.com/likeinlife/cqrs_mediator
